{
  "Monday": {
    "Lunch": [
      {
        "line_name": "green daily",
        "meal_name": "MELANZANE ALLA RICOTTA",
        "meal_description": "Tomato sugo | fried onions | herb polenta",
        "allergens": [
          "gluten wheat",
          "soya",
          "milk, lactose",
          "sesame",
          "Sulfites"
        ],
        "meal_class": [],
        "meat_info": [],
        "fish_info": [],
        "price_info": {
          "students": 6.5,
          "internal": 9.9,
          "external": 14.5
        }
      },
      {
        "line_name": "green delight",
        "meal_name": "Choose 5",
        "meal_description": "Choose 5 components hot or cold",
        "allergens": [],
        "meal_class": [
          "Vegetarian"
        ],
        "meat_info": [],
        "fish_info": [],
        "price_info": {
          "students": 9.9,
          "internal": 12.9,
          "external": 16.9
        }
      }
    ],
    "Dinner": []
  },
  "Tuesday": {
    "Lunch": [
      {
        "line_name": "green daily",
        "meal_name": "VEGAN DAY",
        "meal_description": "Tofu | satay sauce | beans | baby corn | edamame | jasmine rice | lime | ginger\njasmine rice | lime | ginger",
        "allergens": [
          "peanuts",
          "soya",
          "celery",
          "Sulfites"
        ],
        "meal_class": [
          "Vegan",
          "Vegetarian"
        ],
        "meat_info": [],
        "fish_info": [],
        "price_info": {
          "students": 6.5,
          "internal": 9.9,
          "external": 14.5
        }
      },
      {
        "line_name": "green delight",
        "meal_name": "Choose 5",
        "meal_description": "Choose 5 components hot or cold",
        "allergens": [],
        "meal_class": [
          "Vegetarian"
        ],
        "meat_info": [],
        "fish_info": [],
        "price_info": {
          "students": 9.9,
          "internal": 12.9,
          "external": 16.9
        }
      }
    ],
    "Dinner": []
  },
  "Wednesday": {
    "Lunch": [
      {
        "line_name": "green daily",
        "meal_name": "FALAFEL BOWL",
        "meal_description": "Tzatziki sauce | Rice pilaf | Courgette ras el hanout | Fennel | Zatar |",
        "allergens": [
          "gluten wheat",
          "nuts",
          "sesame"
        ],
        "meal_class": [
          "Vegan",
          "Vegetarian"
        ],
        "meat_info": [],
        "fish_info": [],
        "price_info": {
          "students": 6.5,
          "internal": 9.9,
          "external": 14.5
        }
      },
      {
        "line_name": "green delight",
        "meal_name": "Choose 5",
        "meal_description": "Choose 5 components hot or cold",
        "allergens": [],
        "meal_class": [
          "Vegetarian"
        ],
        "meat_info": [],
        "fish_info": [],
        "price_info": {
          "students": 9.9,
          "internal": 12.9,
          "external": 16.9
        }
      }
    ],
    "Dinner": []
  },
  "Thursday": {
    "Lunch": [
      {
        "line_name": "green daily",
        "meal_name": "RÖSTI PICKS",
        "meal_description": "Cream cheese filling | peperonata | kohlrabi | Brussels sprouts | pumpkin seeds",
        "allergens": [
          "eggs",
          "milk, lactose"
        ],
        "meal_class": [
          "Vegetarian"
        ],
        "meat_info": [],
        "fish_info": [],
        "price_info": {
          "students": 6.5,
          "internal": 9.9,
          "external": 14.5
        }
      },
      {
        "line_name": "green delight",
        "meal_name": "Choose 5",
        "meal_description": "Choose 5 components hot or cold",
        "allergens": [],
        "meal_class": [
          "Vegetarian"
        ],
        "meat_info": [],
        "fish_info": [],
        "price_info": {
          "students": 9.9,
          "internal": 12.9,
          "external": 16.9
        }
      }
    ],
    "Dinner": []
  },
  "Friday": {
    "Lunch": [
      {
        "line_name": "green daily",
        "meal_name": "RED LENTIL DAL",
        "meal_description": "fine vegetables | couscous | peas | coriander | fried onions",
        "allergens": [
          "gluten wheat",
          "celery",
          "mustard",
          "Sulfites"
        ],
        "meal_class": [
          "Vegan",
          "Vegetarian"
        ],
        "meat_info": [],
        "fish_info": [],
        "price_info": {
          "students": 6.5,
          "internal": 9.9,
          "external": 14.5
        }
      },
      {
        "line_name": "green delight",
        "meal_name": "Choose 5",
        "meal_description": "Choose 5 components hot or cold",
        "allergens": [],
        "meal_class": [
          "Vegetarian"
        ],
        "meat_info": [],
        "fish_info": [],
        "price_info": {
          "students": 9.9,
          "internal": 12.9,
          "external": 16.9
        }
      }
    ],
    "Dinner": []
  },
  "Saturday": {
    "Lunch": [],
    "Dinner": []
  },
  "Sunday": {
    "Lunch": [],
    "Dinner": []
  }
}